an_debughelper/__init__.py
an_debughelper/debughelper.py
an_debughelper-1.3.3.dist-info/licenses/LICENSE
an_debughelper-1.3.3.dist-info/METADATA
an_debughelper-1.3.3.dist-info/WHEEL
an_debughelper-1.3.3.dist-info/top_level.txt
an_debughelper-1.3.3.dist-info/RECORD
