Metadata-Version: 2.4
Name: an_debughelper
Version: 1.3.3
Summary: A package for an_debughelper.
Home-page: https://github.com/Atsushi888/Atsushi888
Author: Atsushi888
Author-email: Atsushi888 <vtgrotxu@gmail.com>
License: MIT License
Project-URL: Homepage, https://github.com/Atsushi888/an_debughelper
Project-URL: Repository, https://github.com/Atsushi888/an_debughelper
Requires-Python: >=3.6
License-File: LICENSE
Dynamic: author
Dynamic: home-page
Dynamic: license-file
Dynamic: requires-python
